{"@context":"http:\/\/localhost:8888\/omeka-s\/api-context","@id":"http:\/\/localhost:8888\/omeka-s\/api\/items\/4","@type":["o:Item","mov:Films"],"o:id":4,"o:is_public":true,"o:owner":{"@id":"http:\/\/localhost:8888\/omeka-s\/api\/users\/1","o:id":1},"o:resource_class":{"@id":"http:\/\/localhost:8888\/omeka-s\/api\/resource_classes\/109","o:id":109},"o:resource_template":{"@id":"http:\/\/localhost:8888\/omeka-s\/api\/resource_templates\/2","o:id":2},"o:thumbnail":null,"o:title":"SPIDER-MAN: FAR FROM HOME","thumbnail_display_urls":{"large":null,"medium":null,"square":null},"o:created":{"@value":"2021-11-21T13:53:52+00:00","@type":"http:\/\/www.w3.org\/2001\/XMLSchema#dateTime"},"o:modified":{"@value":"2021-11-22T09:12:14+00:00","@type":"http:\/\/www.w3.org\/2001\/XMLSchema#dateTime"},"o:media":[],"o:item_set":[],"o:site":[{"@id":"http:\/\/localhost:8888\/omeka-s\/api\/sites\/1","o:id":1}],"mov:hasTitle":[{"type":"literal","property_id":185,"property_label":"a comme titre","is_public":true,"@value":"SPIDER-MAN: FAR FROM HOME"}],"mov:hasSynopsis":[{"type":"literal","property_id":188,"property_label":"a comme synopsis","is_public":true,"@value":"L\u0027araign\u00e9e sympa du quartier d\u00e9cide de rejoindre ses meilleurs amis Ned, MJ, et le reste de la bande pour des vacances en Europe. Cependant, le projet de Peter de laisser son costume de super-h\u00e9ros derri\u00e8re lui pendant quelques semaines est rapidement compromis quand il accepte \u00e0 contrecoeur d\u0027aider Nick Fury \u00e0 d\u00e9couvrir le myst\u00e8re de plusieurs attaques de cr\u00e9atures, qui ravagent le continent !"}],"mov:hasProducer":[{"type":"literal","property_id":190,"property_label":"a comme producteur","is_public":true,"@value":"Jon Watts"}],"mov:hasGenre":[{"type":"literal","property_id":186,"property_label":"a comme genre","is_public":true,"@value":"Action"}],"mov:hasTrailer":[{"type":"uri","property_id":187,"property_label":"a comme extrait video","is_public":true,"@id":"https:\/\/www.youtube.com\/watch?v=Nt9L1jCKGnE\u0026ab_channel=SonyPicturesEntertainment","o:label":"Lien Youtube vers le trailer"}],"mov:hasDuration":[{"type":"literal","property_id":191,"property_label":"a comme duree","is_public":true,"@value":"2h 10min"}],"mov:hasActors":[{"type":"literal","property_id":189,"property_label":"a comme acteur","is_public":true,"@value":"Tom Holland, Jake Gyllenhaal, Zendaya"}],"dcterms:title":[{"type":"literal","property_id":1,"property_label":"Title","is_public":true,"@value":"SPIDER-MAN: FAR FROM HOME"}],"dcterms:description":[{"type":"literal","property_id":4,"property_label":"Description","is_public":true,"@value":"Description du film SPIDER-MAN: FAR FROM HOME"}]}